deside/__init__.py
deside/bulk_cell/__init__.py
deside/bulk_cell/preprocessing.py
deside/decon_cf/__init__.py
deside/decon_cf/deside.py
deside/plot/__init__.py
deside/plot/evaluate_result.py
deside/plot/plot_clustering.py
deside/plot/plot_gene.py
deside/plot/plot_nn.py
deside/plot/plot_sample.py
deside/simulation/__init__.py
deside/simulation/generate_data.py
deside/simulation/stats_test.py
deside/single_cell/__init__.py
deside/single_cell/preprocessing.py
deside/utility/__init__.py
deside/utility/compare.py
deside/utility/core_obj.py
deside/utility/evaluation.py
deside/utility/pub_func.py
deside/utility/read_file.py
deside/workflow/__init__.py
deside/workflow/workflow.py
DeSide-1.3.2.dist-info/LICENSE
DeSide-1.3.2.dist-info/METADATA
DeSide-1.3.2.dist-info/WHEEL
DeSide-1.3.2.dist-info/top_level.txt
DeSide-1.3.2.dist-info/RECORD
