Metadata-Version: 2.1
Name: DeSide
Version: 1.3.2
Summary: A unified DEep-learning and SIngle-cell based DEconvolution method for solid tumors
Author-email: OnlyBelter <onlybelter@outlook.com>
License: MIT License
Project-URL: Homepage, https://github.com/OnlyBelter/DeSide
Project-URL: Source, https://github.com/OnlyBelter/DeSide
Project-URL: Tracker, https://github.com/OnlyBelter/DeSide/issues
Keywords: DeSide,RNA-seq,deconvolution
Classifier: Intended Audience :: Science/Research
Classifier: License :: OSI Approved :: BSD License
Classifier: Programming Language :: Python
Classifier: Programming Language :: Python :: 3.8
Classifier: Programming Language :: Python :: 3.9
Classifier: Programming Language :: Python :: 3.10
Classifier: Programming Language :: Python :: 3.11
Classifier: Typing :: Typed
Requires-Python: >=3.8
License-File: LICENSE
Requires-Dist: tensorflow==2.11.1
Requires-Dist: scikit-learn==0.24.2
Requires-Dist: anndata>=0.8.0
Requires-Dist: scanpy==1.8.0
Requires-Dist: pandas==1.5.3
Requires-Dist: numpy>=1.22
Requires-Dist: scipy
Requires-Dist: umap-learn==0.5.1
Requires-Dist: matplotlib<3.7
Requires-Dist: seaborn==0.12.0
Requires-Dist: bbknn==1.5.1
Requires-Dist: SciencePlots
Requires-Dist: tables==3.6.1
Requires-Dist: build
Requires-Dist: sphinx>=6.0
Requires-Dist: myst-parser>=0.13.6
Requires-Dist: fsspec
Requires-Dist: h5py
Requires-Dist: jinja2<3.1
Requires-Dist: numba<0.57
